Metadata-Version: 1.0
Name: when-will-it-end
Version: 0.0.2
Summary: A simpler progress monitor
Home-page: https://github.com/zkurtz/when_will_it_end
Author: Zach Kurtz
Author-email: zkurtz@gmail.com
License: MIT
Platform: UNKNOWN
